{
  "group_name": "shadows blur",
  "source_name": "shadows_blur.fx",

  "entrypoints": {
    "main_vs": {
      "stage": "vertex",

      "vertex_state": {
        "generic_input": {
          "dynamic_compression": false,
          "position": false,
          "skinned": false,
          "normal": false,
          "tangents": false,
          "color": false,
          "texture_coords": false
        }
      }
    },

    "blur_ps": {
      "stage": "pixel",

      "pixel_state": {
        "lighting": false
      }
    },

    "combine_ps": {
      "stage": "pixel",

      "pixel_state": {
        "lighting": false
      }
    }
  },

  "rendertypes": { "shadows blur": {} },

  "states": {
    "blur": {
      "type": "standard",

      "vertex_shader": {
        "entrypoint": "main_vs"
      },

      "pixel_shader": {
        "entrypoint": "blur_ps"
      }
    },

    "combine depth": {
      "type": "standard",

      "vertex_shader": {
        "entrypoint": "main_vs"
      },

      "pixel_shader": {
        "entrypoint": "combine_ps"
      }
    }
  }
}